easy_pmf/__init__.py
easy_pmf/cli.py
easy_pmf/py.typed
easy_pmf/data/Dataset-Baltimore_con.txt
easy_pmf/data/Dataset-Baltimore_unc.txt
easy_pmf/data/Dataset-Baltimore_unc_eqn.txt
easy_pmf/data/Dataset-BatonRouge-con.csv
easy_pmf/data/Dataset-BatonRouge-unc.csv
easy_pmf/data/Dataset-StLouis-con.csv
easy_pmf/data/Dataset-StLouis-unc.csv
easy_pmf-0.1.0.dist-info/licenses/LICENSE
easy_pmf-0.1.0.dist-info/METADATA
easy_pmf-0.1.0.dist-info/WHEEL
easy_pmf-0.1.0.dist-info/entry_points.txt
easy_pmf-0.1.0.dist-info/top_level.txt
easy_pmf-0.1.0.dist-info/RECORD
