Metadata-Version: 2.4
Name: easy-pmf
Version: 0.1.0
Summary: An easy-to-use package for Positive Matrix Factorization (PMF) analysis of environmental data.
Author-email: Gerrit Jan de Bruin <gerritjan.debruin@gmail.com>
License: MIT
Project-URL: Homepage, https://github.com/easy-pmf/easy-pmf
Project-URL: Documentation, https://easy-pmf.readthedocs.io
Project-URL: Repository, https://github.com/easy-pmf/easy-pmf
Project-URL: Bug Tracker, https://github.com/easy-pmf/easy-pmf/issues
Project-URL: Changelog, https://github.com/easy-pmf/easy-pmf/blob/main/CHANGELOG.md
Keywords: pmf,positive matrix factorization,environmental,air quality,source apportionment
Classifier: Development Status :: 4 - Beta
Classifier: Intended Audience :: Science/Research
Classifier: Topic :: Scientific/Engineering :: Atmospheric Science
Classifier: Topic :: Scientific/Engineering :: Chemistry
Classifier: Programming Language :: Python :: 3
Classifier: Programming Language :: Python :: 3.9
Classifier: Programming Language :: Python :: 3.10
Classifier: Programming Language :: Python :: 3.11
Classifier: Programming Language :: Python :: 3.12
Classifier: Operating System :: OS Independent
Requires-Python: >=3.9
License-File: LICENSE
Requires-Dist: matplotlib>=3.5.0
Requires-Dist: numpy>=1.20.0
Requires-Dist: pandas>=1.3.0
Requires-Dist: seaborn>=0.11.0
Dynamic: license-file
